README.md
setup.py
ODtools/__init__.py
ODtools/bloom_filter_tools.py
ODtools/excel_tools.py
ODtools/fastdfs_tools.py
ODtools/hbase_tools.py
ODtools/kafka_tools.py
ODtools/log_tools.py
ODtools/monitor_tools.py
ODtools/monitor_tools_new.py
ODtools/redis_tools.py
ODtools/request_headers.py
ODtools/save_data_class.py
ODtools/singleton_tools.py
ODtools/time_counter.py
ODtools/timeit_counter.py
ODtools.egg-info/PKG-INFO
ODtools.egg-info/SOURCES.txt
ODtools.egg-info/dependency_links.txt
ODtools.egg-info/requires.txt
ODtools.egg-info/top_level.txt
ODtools.egg-info/zip-safe
ODtools/fdfs_client/__init__.py
ODtools/fdfs_client/client.py
ODtools/fdfs_client/connection.py
ODtools/fdfs_client/exceptions.py
ODtools/fdfs_client/fdfs_protol.py
ODtools/fdfs_client/fdfs_test.py
ODtools/fdfs_client/storage_client.py
ODtools/fdfs_client/tracker_client.py
ODtools/fdfs_client/utils.py
ODtools/hbase_client/THBaseService.py
ODtools/hbase_client/__init__.py
ODtools/hbase_client/constants.py
ODtools/hbase_client/ttypes.py
ODtools/scrapy_redis/__init__.py
ODtools/scrapy_redis/connection.py
ODtools/scrapy_redis/defaults.py
ODtools/scrapy_redis/dupefilter.py
ODtools/scrapy_redis/picklecompat.py
ODtools/scrapy_redis/pipelines.py
ODtools/scrapy_redis/queue.py
ODtools/scrapy_redis/scheduler.py
ODtools/scrapy_redis/spiders.py
ODtools/scrapy_redis/utils.py